ap_ds/GUI_TEST.py
ap_ds/__init__.py
ap_ds/audio_info.py
ap_ds/audio_parser.py
ap_ds/player.py
ap_ds-2.3.0.dist-info/licenses/LICENSE.md
ap_ds-2.3.0.dist-info/METADATA
ap_ds-2.3.0.dist-info/WHEEL
ap_ds-2.3.0.dist-info/top_level.txt
ap_ds-2.3.0.dist-info/RECORD
